vlppy/LICENSE.txt
vlppy/__init__.py
vlppy/info.py
vlppy/.vscode/settings.json
vlppy/demo/README.md
vlppy/demo/__init__.py
vlppy/demo/demo_filter.py
vlppy/demo/demo_main.py
vlppy/demo/vlp_model.py
vlppy/demo/__pycache__/__init__.cpython-39.pyc
vlppy/demo/__pycache__/demo_main.cpython-39.pyc
vlppy/demo/__pycache__/vlp_model.cpython-39.pyc
vlppy/error/__init__.py
vlppy/error/error.py
vlppy/io/__init__.py
vlppy/io/io.py
vlppy/model/__init__.py
vlppy/model/led.py
vlppy/model/pd.py
vlppy/model/room.py
vlppy/model/__pycache__/__init__.cpython-39.pyc
vlppy/model/__pycache__/filter.cpython-39.pyc
vlppy/model/__pycache__/led.cpython-39.pyc
vlppy/model/__pycache__/pd.cpython-39.pyc
vlppy/model/__pycache__/room.cpython-39.pyc
vlppy/setting/__init__.py
vlppy/setting/json_setting.py
vlppy/setting/settings.json
vlppy/setting/__pycache__/__init__.cpython-39.pyc
vlppy/setting/__pycache__/json_setting.cpython-39.pyc
vlppy/signal/__init__.py
vlppy/signal/filter.py
vlppy/signal/plot.py
vlppy/tools/__init__.py
vlppy/tools/decorator.py
vlppy/vis/__init__.py
vlppy/vis/vis.py
yang_vlp-0.2.20.dist-info/LICENSE
yang_vlp-0.2.20.dist-info/METADATA
yang_vlp-0.2.20.dist-info/WHEEL
yang_vlp-0.2.20.dist-info/top_level.txt
yang_vlp-0.2.20.dist-info/RECORD
