Metadata-Version: 2.1
Name: yang-vlp
Version: 0.2.20
Summary: Construction of visible light positioning model
Home-page: https://gitee.com/yangwuju/yang_vlp
Author: yangwuju
Author-email: yangwuju <1424134319@qq.com>
License: Copyright (c) 2018 The Python Packaging Authority
Project-URL: Homepage, https://gitee.com/yangwuju/yang_vlp
Project-URL: Bug Tracker, https://gitee.com/yangwuju/yang_vlp/issues
Classifier: Programming Language :: Python :: 3
Classifier: License :: OSI Approved :: MIT License
Classifier: Operating System :: OS Independent
Requires-Python: >=3.5
License-File: LICENSE
Requires-Dist: numpy (>=1.19.0)
Requires-Dist: matplotlib (>=3.5.0)
Requires-Dist: scipy (>=1.8.0)
Requires-Dist: pandas (>=1.3.0)
